enterble/__init__.py
enterble/__version__.py
enterble/adapter/__init__.py
enterble/adapter/flowtime/__init__.py
enterble/adapter/flowtime/collector.py
enterble/ble/__init__.py
enterble/ble/config.py
enterble/ble/device.py
enterble/ble/scanner.py
enterble/collector/__init__.py
enterble/collector/collector.py
enterble-1.1.1.dist-info/LICENSE
enterble-1.1.1.dist-info/METADATA
enterble-1.1.1.dist-info/WHEEL
enterble-1.1.1.dist-info/top_level.txt
enterble-1.1.1.dist-info/RECORD
